LICENSE
LICENSE.txt
README.rst
setup.cfg
setup.py
eisenheimisme/__init__.py
eisenheimisme/eisenheim.py
eisenheimisme.egg-info/PKG-INFO
eisenheimisme.egg-info/SOURCES.txt
eisenheimisme.egg-info/dependency_links.txt
eisenheimisme.egg-info/top_level.txt